hplc/__init__.py
hplc/io.py
hplc/quant.py
hplc_py-0.2.10.dist-info/LICENSE
hplc_py-0.2.10.dist-info/METADATA
hplc_py-0.2.10.dist-info/WHEEL
hplc_py-0.2.10.dist-info/top_level.txt
hplc_py-0.2.10.dist-info/RECORD
