Metadata-Version: 2.1
Name: hplc-py
Version: 0.2.10
Summary: Python utilities for the processing and quantification of chromatograms from High Performance Liquid Chromatography (HPLC).
Home-page: https://github.com/cremerlab/hplc-py
Author: Griffin Chure
Author-email: griffinchure@gmail.com
License: GPLv3
Classifier: Development Status :: 4 - Beta
Classifier: Intended Audience :: Science/Research
Classifier: Programming Language :: Python :: 3
License-File: LICENSE
